docs/Makefile
docs/changelog.rst
docs/conf.py
docs/index.rst
docs/requirements.txt
ocdskingfishercolab/__init__.py
ocdskingfishercolab-0.6.0.dist-info/licenses/LICENSE
ocdskingfishercolab-0.6.0.dist-info/METADATA
ocdskingfishercolab-0.6.0.dist-info/WHEEL
ocdskingfishercolab-0.6.0.dist-info/top_level.txt
ocdskingfishercolab-0.6.0.dist-info/RECORD
