Metadata-Version: 2.4
Name: ocdskingfishercolab
Version: 0.6.0
Summary: A set of utility functions for Google Colab notebooks using OCDS data
Author-email: Open Contracting Partnership <data@open-contracting.org>
License: BSD
Project-URL: Homepage, https://github.com/open-contracting/kingfisher-colab
Classifier: License :: OSI Approved :: BSD License
Classifier: Operating System :: POSIX :: Linux
Classifier: Programming Language :: Python :: 3.12
Classifier: Programming Language :: Python :: Implementation :: CPython
License-File: LICENSE
Requires-Dist: babel
Requires-Dist: flattentool
Requires-Dist: google-auth
Requires-Dist: gspread
Requires-Dist: gspread-dataframe
Requires-Dist: httplib2
Requires-Dist: ipython
Requires-Dist: ipython-sql
Requires-Dist: jupyter_server
Requires-Dist: matplotlib
Requires-Dist: oauth2client
Requires-Dist: prettytable<3.12
Requires-Dist: pydrive2
Requires-Dist: requests
Requires-Dist: seaborn
Requires-Dist: sqlalchemy
Provides-Extra: test
Requires-Dist: pandas; extra == "test"
Requires-Dist: psycopg2-binary; extra == "test"
Requires-Dist: pytest; extra == "test"
Requires-Dist: pytest-cov; extra == "test"
Dynamic: license-file
